splicejsonmultipleroots/__init__.py
splicejsonmultipleroots/example.py
splicejsonmultipleroots_thestrugglingdeveloper-0.1.1.dist-info/LICENSE
splicejsonmultipleroots_thestrugglingdeveloper-0.1.1.dist-info/METADATA
splicejsonmultipleroots_thestrugglingdeveloper-0.1.1.dist-info/WHEEL
splicejsonmultipleroots_thestrugglingdeveloper-0.1.1.dist-info/top_level.txt
splicejsonmultipleroots_thestrugglingdeveloper-0.1.1.dist-info/RECORD
