Metadata-Version: 2.1
Name: splicejsonmultipleroots-thestrugglingdeveloper
Version: 0.1.1
Summary: A small package to extract an array of json root elements
Home-page: https://github.com/thestrugglingdeveloper/splicejsonmultipleroots
Author: TheStrugglingDeveloper
Author-email: github@thestrugglingdeveloper.com
License: UNKNOWN
Platform: UNKNOWN
Classifier: Programming Language :: Python :: 3
Classifier: License :: OSI Approved :: MIT License
Classifier: Operating System :: OS Independent
Requires-Python: >=3.6
